basile/__init__.py
basile/basile.py
basile-1.0.0.dist-info/LICENSE
basile-1.0.0.dist-info/METADATA
basile-1.0.0.dist-info/WHEEL
basile-1.0.0.dist-info/top_level.txt
basile-1.0.0.dist-info/RECORD
