Metadata-Version: 2.1
Name: basile
Version: 1.0.0
Summary: A lightweight, brute-force framework for discrete code-based experimentations
Author: Thomas VIAL
Project-URL: Homepage, https://github.com/tvial/basile
Project-URL: Issues, https://github.com/tvial/basile/issues
Classifier: Programming Language :: Python :: 3
Classifier: License :: OSI Approved :: MIT License
Classifier: Operating System :: OS Independent
Requires-Python: >=3.8
License-File: LICENSE
